[{"_Id":1030101,"_OrbData1Id1":104001011,"_OrbData2Id1":0,"_OrbData3Id1":0,"_OrbData4Id1":0,"_OrbData5Id1":0,"_OrbData1Num1":5,"_OrbData2Num1":0,"_OrbData3Num1":0,"_OrbData4Num1":0,"_OrbData5Num1":0,"_UniqueGrowMaterial1Num1":0,"_UniqueGrowMaterial2Num1":0,"_GrowMaterialNum1":1,"_OrbData1Id2":104001011,"_OrbData2Id2":104001012,"_OrbData3Id2":0,"_OrbData4Id2":0,"_OrbData5Id2":0,"_OrbData1Num2":10,"_OrbData2Num2":3,"_OrbData3Num2":0,"_OrbData4Num2":0,"_OrbData5Num2":0,"_UniqueGrowMaterial1Num2":0,"_UniqueGrowMaterial2Num2":0,"_GrowMaterialNum2":1,"_OrbData1Id3":104001012,"_OrbData2Id3":104001013,"_OrbData3Id3":104002011,"_OrbData4Id3":104002012,"_OrbData5Id3":0,"_OrbData1Num3":5,"_OrbData2Num3":1,"_OrbData3Num3":10,"_OrbData4Num3":3,"_OrbData5Num3":0,"_UniqueGrowMaterial1Num3":0,"_UniqueGrowMaterial2Num3":0,"_GrowMaterialNum3":1,"_OrbData1Id4":104001013,"_OrbData2Id4":104001001,"_OrbData3Id4":104002011,"_OrbData4Id4":104002012,"_OrbData5Id4":104003001,"_OrbData1Num4":4,"_OrbData2Num4":1,"_OrbData3Num4":15,"_OrbData4Num4":5,"_OrbData5Num4":1,"_UniqueGrowMaterial1Num4":0,"_UniqueGrowMaterial2Num4":0,"_GrowMaterialNum4":1,"_OrbData1Id5":104001013,"_OrbData2Id5":104001001,"_OrbData3Id5":104002012,"_OrbData4Id5":201014002,"_OrbData5Id5":104003001,"_OrbData1Num5":6,"_OrbData2Num5":12,"_OrbData3Num5":9,"_OrbData4Num5":6,"_OrbData5Num5":1,"_UniqueGrowMaterial1Num5":0,"_UniqueGrowMaterial2Num5":0,"_GrowMaterialNum5":1},{"_Id":1030102,"_OrbData1Id1":104001021,"_OrbData2Id1":0,"_OrbData3Id1":0,"_OrbData4Id1":0,"_OrbData5Id1":0,"_OrbData1Num1":5,"_OrbData2Num1":0,"_OrbData3Num1":0,"_OrbData4Num1":0,"_OrbData5Num1":0,"_UniqueGrowMaterial1Num1":0,"_UniqueGrowMaterial2Num1":0,"_GrowMaterialNum1":1,"_OrbData1Id2":104001021,"_OrbData2Id2":104001022,"_OrbData3Id2":0,"_OrbData4Id2":0,"_OrbData5Id2":0,"_OrbData1Num2":10,"_OrbData2Num2":3,"_OrbData3Num2":0,"_OrbData4Num2":0,"_OrbData5Num2":0,"_UniqueGrowMaterial1Num2":0,"_UniqueGrowMaterial2Num2":0,"_GrowMaterialNum2":1,"_OrbData1Id3":104001022,"_OrbData2Id3":104001023,"_OrbData3Id3":104002021,"_OrbData4Id3":104002022,"_OrbData5Id3":0,"_OrbData1Num3":5,"_OrbData2Num3":1,"_OrbData3Num3":10,"_OrbData4Num3":3,"_OrbData5Num3":0,"_UniqueGrowMaterial1Num3":0,"_UniqueGrowMaterial2Num3":0,"_GrowMaterialNum3":1,"_OrbData1Id4":104001023,"_OrbData2Id4":104001001,"_OrbData3Id4":104002021,"_OrbData4Id4":104002022,"_OrbData5Id4":104003001,"_OrbData1Num4":4,"_OrbData2Num4":1,"_OrbData3Num4":15,"_OrbData4Num4":5,"_OrbData5Num4":1,"_UniqueGrowMaterial1Num4":0,"_UniqueGrowMaterial2Num4":0,"_GrowMaterialNum4":1,"_OrbData1Id5":104001023,"_OrbData2Id5":104001001,"_OrbData3Id5":104002022,"_OrbData4Id5":201014002,"_OrbData5Id5":104003001,"_OrbData1Num5":6,"_OrbData2Num5":12,"_OrbData3Num5":9,"_OrbData4Num5":6,"_OrbData5Num5":1,"_UniqueGrowMaterial1Num5":0,"_UniqueGrowMaterial2Num5":0,"_GrowMaterialNum5":1},{"_Id":1030103,"_OrbData1Id1":104001031,"_OrbData2Id1":0,"_OrbData3Id1":0,"_OrbData4Id1":0,"_OrbData5Id1":0,"_OrbData1Num1":5,"_OrbData2Num1":0,"_OrbData3Num1":0,"_OrbData4Num1":0,"_OrbData5Num1":0,"_UniqueGrowMaterial1Num1":0,"_UniqueGrowMaterial2Num1":0,"_GrowMaterialNum1":1,"_OrbData1Id2":104001031,"_OrbData2Id2":104001032,"_OrbData3Id2":0,"_OrbData4Id2":0,"_OrbData5Id2":0,"_OrbData1Num2":10,"_OrbData2Num2":3,"_OrbData3Num2":0,"_OrbData4Num2":0,"_OrbData5Num2":0,"_UniqueGrowMaterial1Num2":0,"_UniqueGrowMaterial2Num2":0,"_GrowMaterialNum2":1,"_OrbData1Id3":104001032,"_OrbData2Id3":104001033,"_OrbData3Id3":104002031,"_OrbData4Id3":104002032,"_OrbData5Id3":0,"_OrbData1Num3":5,"_OrbData2Num3":1,"_OrbData3Num3":10,"_OrbData4Num3":3,"_OrbData5Num3":0,"_UniqueGrowMaterial1Num3":0,"_UniqueGrowMaterial2Num3":0,"_GrowMaterialNum3":1,"_OrbData1Id4":104001033,"_OrbData2Id4":104001001,"_OrbData3Id4":104002031,"_OrbData4Id4":104002032,"_OrbData5Id4":104003001,"_OrbData1Num4":4,"_OrbData2Num4":1,"_OrbData3Num4":15,"_OrbData4Num4":5,"_OrbData5Num4":1,"_UniqueGrowMaterial1Num4":0,"_UniqueGrowMaterial2Num4":0,"_GrowMaterialNum4":1,"_OrbData1Id5":104001033,"_OrbData2Id5":104001001,"_OrbData3Id5":104002032,"_OrbData4Id5":201014002,"_OrbData5Id5":104003001,"_OrbData1Num5":6,"_OrbData2Num5":12,"_OrbData3Num5":9,"_OrbData4Num5":6,"_OrbData5Num5":1,"_UniqueGrowMaterial1Num5":0,"_UniqueGrowMaterial2Num5":0,"_GrowMaterialNum5":1},{"_Id":1030104,"_OrbData1Id1":104001041,"_OrbData2Id1":0,"_OrbData3Id1":0,"_OrbData4Id1":0,"_OrbData5Id1":0,"_OrbData1Num1":5,"_OrbData2Num1":0,"_OrbData3Num1":0,"_OrbData4Num1":0,"_OrbData5Num1":0,"_UniqueGrowMaterial1Num1":0,"_UniqueGrowMaterial2Num1":0,"_GrowMaterialNum1":1,"_OrbData1Id2":104001041,"_OrbData2Id2":104001042,"_OrbData3Id2":0,"_OrbData4Id2":0,"_OrbData5Id2":0,"_OrbData1Num2":10,"_OrbData2Num2":3,"_OrbData3Num2":0,"_OrbData4Num2":0,"_OrbData5Num2":0,"_UniqueGrowMaterial1Num2":0,"_UniqueGrowMaterial2Num2":0,"_GrowMaterialNum2":1,"_OrbData1Id3":104001042,"_OrbData2Id3":104001043,"_OrbData3Id3":104002041,"_OrbData4Id3":104002042,"_OrbData5Id3":0,"_OrbData1Num3":5,"_OrbData2Num3":1,"_OrbData3Num3":10,"_OrbData4Num3":3,"_OrbData5Num3":0,"_UniqueGrowMaterial1Num3":0,"_UniqueGrowMaterial2Num3":0,"_GrowMaterialNum3":1,"_OrbData1Id4":104001043,"_OrbData2Id4":104001001,"_OrbData3Id4":104002041,"_OrbData4Id4":104002042,"_OrbData5Id4":104003001,"_OrbData1Num4":4,"_OrbData2Num4":1,"_OrbData3Num4":15,"_OrbData4Num4":5,"_OrbData5Num4":1,"_UniqueGrowMaterial1Num4":0,"_UniqueGrowMaterial2Num4":0,"_GrowMaterialNum4":1,"_OrbData1Id5":104001043,"_OrbData2Id5":104001001,"_OrbData3Id5":104002042,"_OrbData4Id5":201014002,"_OrbData5Id5":104003001,"_OrbData1Num5":6,"_OrbData2Num5":12,"_OrbData3Num5":9,"_OrbData4Num5":6,"_OrbData5Num5":1,"_UniqueGrowMaterial1Num5":0,"_UniqueGrowMaterial2Num5":0,"_GrowMaterialNum5":1},{"_Id":1030105,"_OrbData1Id1":104001051,"_OrbData2Id1":0,"_OrbData3Id1":0,"_OrbData4Id1":0,"_OrbData5Id1":0,"_OrbData1Num1":5,"_OrbData2Num1":0,"_OrbData3Num1":0,"_OrbData4Num1":0,"_OrbData5Num1":0,"_UniqueGrowMaterial1Num1":0,"_UniqueGrowMaterial2Num1":0,"_GrowMaterialNum1":1,"_OrbData1Id2":104001051,"_OrbData2Id2":104001052,"_OrbData3Id2":0,"_OrbData4Id2":0,"_OrbData5Id2":0,"_OrbData1Num2":10,"_OrbData2Num2":3,"_OrbData3Num2":0,"_OrbData4Num2":0,"_OrbData5Num2":0,"_UniqueGrowMaterial1Num2":0,"_UniqueGrowMaterial2Num2":0,"_GrowMaterialNum2":1,"_OrbData1Id3":104001052,"_OrbData2Id3":104001053,"_OrbData3Id3":104002051,"_OrbData4Id3":104002052,"_OrbData5Id3":0,"_OrbData1Num3":5,"_OrbData2Num3":1,"_OrbData3Num3":10,"_OrbData4Num3":3,"_OrbData5Num3":0,"_UniqueGrowMaterial1Num3":0,"_UniqueGrowMaterial2Num3":0,"_GrowMaterialNum3":1,"_OrbData1Id4":104001053,"_OrbData2Id4":104001001,"_OrbData3Id4":104002051,"_OrbData4Id4":104002052,"_OrbData5Id4":104003001,"_OrbData1Num4":4,"_OrbData2Num4":1,"_OrbData3Num4":15,"_OrbData4Num4":5,"_OrbData5Num4":1,"_UniqueGrowMaterial1Num4":0,"_UniqueGrowMaterial2Num4":0,"_GrowMaterialNum4":1,"_OrbData1Id5":104001053,"_OrbData2Id5":104001001,"_OrbData3Id5":104002052,"_OrbData4Id5":201014002,"_OrbData5Id5":104003001,"_OrbData1Num5":6,"_OrbData2Num5":12,"_OrbData3Num5":9,"_OrbData4Num5":6,"_OrbData5Num5":1,"_UniqueGrowMaterial1Num5":0,"_UniqueGrowMaterial2Num5":0,"_GrowMaterialNum5":1},{"_Id":1040201,"_OrbData1Id1":104001011,"_OrbData2Id1":0,"_OrbData3Id1":0,"_OrbData4Id1":0,"_OrbData5Id1":0,"_OrbData1Num1":7,"_OrbData2Num1":0,"_OrbData3Num1":0,"_OrbData4Num1":0,"_OrbData5Num1":0,"_UniqueGrowMaterial1Num1":0,"_UniqueGrowMaterial2Num1":0,"_GrowMaterialNum1":1,"_OrbData1Id2":104001011,"_OrbData2Id2":104001012,"_OrbData3Id2":0,"_OrbData4Id2":0,"_OrbData5Id2":0,"_OrbData1Num2":12,"_OrbData2Num2":3,"_OrbData3Num2":0,"_OrbData4Num2":0,"_OrbData5Num2":0,"_UniqueGrowMaterial1Num2":0,"_UniqueGrowMaterial2Num2":0,"_GrowMaterialNum2":1,"_OrbData1Id3":104001012,"_OrbData2Id3":104001013,"_OrbData3Id3":104001001,"_OrbData4Id3":104002011,"_OrbData5Id3":104002012,"_OrbData1Num3":5,"_OrbData2Num3":3,"_OrbData3Num3":1,"_OrbData4Num3":15,"_OrbData5Num3":5,"_UniqueGrowMaterial1Num3":0,"_UniqueGrowMaterial2Num3":0,"_GrowMaterialNum3":1,"_OrbData1Id4":104001013,"_OrbData2Id4":104001001,"_OrbData3Id4":104002011,"_OrbData4Id4":104002012,"_OrbData5Id4":104003001,"_OrbData1Num4":4,"_OrbData2Num4":1,"_OrbData3Num4":20,"_OrbData4Num4":7,"_OrbData5Num4":2,"_UniqueGrowMaterial1Num4":0,"_UniqueGrowMaterial2Num4":0,"_GrowMaterialNum4":1,"_OrbData1Id5":104001013,"_OrbData2Id5":104001001,"_OrbData3Id5":104002012,"_OrbData4Id5":201014002,"_OrbData5Id5":104003001,"_OrbData1Num5":8,"_OrbData2Num5":16,"_OrbData3Num5":12,"_OrbData4Num5":8,"_OrbData5Num5":2,"_UniqueGrowMaterial1Num5":0,"_UniqueGrowMaterial2Num5":0,"_GrowMaterialNum5":1},{"_Id":1040202,"_OrbData1Id1":104001021,"_OrbData2Id1":0,"_OrbData3Id1":0,"_OrbData4Id1":0,"_OrbData5Id1":0,"_OrbData1Num1":7,"_OrbData2Num1":0,"_OrbData3Num1":0,"_OrbData4Num1":0,"_OrbData5Num1":0,"_UniqueGrowMaterial1Num1":0,"_UniqueGrowMaterial2Num1":0,"_GrowMaterialNum1":1,"_OrbData1Id2":104001021,"_OrbData2Id2":104001022,"_OrbData3Id2":0,"_OrbData4Id2":0,"_OrbData5Id2":0,"_OrbData1Num2":12,"_OrbData2Num2":3,"_OrbData3Num2":0,"_OrbData4Num2":0,"_OrbData5Num2":0,"_UniqueGrowMaterial1Num2":0,"_UniqueGrowMaterial2Num2":0,"_GrowMaterialNum2":1,"_OrbData1Id3":104001022,"_OrbData2Id3":104001023,"_OrbData3Id3":104001001,"_OrbData4Id3":104002021,"_OrbData5Id3":104002022,"_OrbData1Num3":5,"_OrbData2Num3":3,"_OrbData3Num3":1,"_OrbData4Num3":15,"_OrbData5Num3":5,"_UniqueGrowMaterial1Num3":0,"_UniqueGrowMaterial2Num3":0,"_GrowMaterialNum3":1,"_OrbData1Id4":104001023,"_OrbData2Id4":104001001,"_OrbData3Id4":104002021,"_OrbData4Id4":104002022,"_OrbData5Id4":104003001,"_OrbData1Num4":4,"_OrbData2Num4":1,"_OrbData3Num4":20,"_OrbData4Num4":7,"_OrbData5Num4":2,"_UniqueGrowMaterial1Num4":0,"_UniqueGrowMaterial2Num4":0,"_GrowMaterialNum4":1,"_OrbData1Id5":104001023,"_OrbData2Id5":104001001,"_OrbData3Id5":104002022,"_OrbData4Id5":201014002,"_OrbData5Id5":104003001,"_OrbData1Num5":8,"_OrbData2Num5":16,"_OrbData3Num5":12,"_OrbData4Num5":8,"_OrbData5Num5":2,"_UniqueGrowMaterial1Num5":0,"_UniqueGrowMaterial2Num5":0,"_GrowMaterialNum5":1},{"_Id":1040203,"_OrbData1Id1":104001031,"_OrbData2Id1":0,"_OrbData3Id1":0,"_OrbData4Id1":0,"_OrbData5Id1":0,"_OrbData1Num1":7,"_OrbData2Num1":0,"_OrbData3Num1":0,"_OrbData4Num1":0,"_OrbData5Num1":0,"_UniqueGrowMaterial1Num1":0,"_UniqueGrowMaterial2Num1":0,"_GrowMaterialNum1":1,"_OrbData1Id2":104001031,"_OrbData2Id2":104001032,"_OrbData3Id2":0,"_OrbData4Id2":0,"_OrbData5Id2":0,"_OrbData1Num2":12,"_OrbData2Num2":3,"_OrbData3Num2":0,"_OrbData4Num2":0,"_OrbData5Num2":0,"_UniqueGrowMaterial1Num2":0,"_UniqueGrowMaterial2Num2":0,"_GrowMaterialNum2":1,"_OrbData1Id3":104001032,"_OrbData2Id3":104001033,"_OrbData3Id3":104001001,"_OrbData4Id3":104002031,"_OrbData5Id3":104002032,"_OrbData1Num3":5,"_OrbData2Num3":3,"_OrbData3Num3":1,"_OrbData4Num3":15,"_OrbData5Num3":5,"_UniqueGrowMaterial1Num3":0,"_UniqueGrowMaterial2Num3":0,"_GrowMaterialNum3":1,"_OrbData1Id4":104001033,"_OrbData2Id4":104001001,"_OrbData3Id4":104002031,"_OrbData4Id4":104002032,"_OrbData5Id4":104003001,"_OrbData1Num4":4,"_OrbData2Num4":1,"_OrbData3Num4":20,"_OrbData4Num4":7,"_OrbData5Num4":2,"_UniqueGrowMaterial1Num4":0,"_UniqueGrowMaterial2Num4":0,"_GrowMaterialNum4":1,"_OrbData1Id5":104001033,"_OrbData2Id5":104001001,"_OrbData3Id5":104002032,"_OrbData4Id5":201014002,"_OrbData5Id5":104003001,"_OrbData1Num5":8,"_OrbData2Num5":16,"_OrbData3Num5":12,"_OrbData4Num5":8,"_OrbData5Num5":2,"_UniqueGrowMaterial1Num5":0,"_UniqueGrowMaterial2Num5":0,"_GrowMaterialNum5":1},{"_Id":1040204,"_OrbData1Id1":104001041,"_OrbData2Id1":0,"_OrbData3Id1":0,"_OrbData4Id1":0,"_OrbData5Id1":0,"_OrbData1Num1":7,"_OrbData2Num1":0,"_OrbData3Num1":0,"_OrbData4Num1":0,"_OrbData5Num1":0,"_UniqueGrowMaterial1Num1":0,"_UniqueGrowMaterial2Num1":0,"_GrowMaterialNum1":1,"_OrbData1Id2":104001041,"_OrbData2Id2":104001042,"_OrbData3Id2":0,"_OrbData4Id2":0,"_OrbData5Id2":0,"_OrbData1Num2":12,"_OrbData2Num2":3,"_OrbData3Num2":0,"_OrbData4Num2":0,"_OrbData5Num2":0,"_UniqueGrowMaterial1Num2":0,"_UniqueGrowMaterial2Num2":0,"_GrowMaterialNum2":1,"_OrbData1Id3":104001042,"_OrbData2Id3":104001043,"_OrbData3Id3":104001001,"_OrbData4Id3":104002041,"_OrbData5Id3":104002042,"_OrbData1Num3":5,"_OrbData2Num3":3,"_OrbData3Num3":1,"_OrbData4Num3":15,"_OrbData5Num3":5,"_UniqueGrowMaterial1Num3":0,"_UniqueGrowMaterial2Num3":0,"_GrowMaterialNum3":1,"_OrbData1Id4":104001043,"_OrbData2Id4":104001001,"_OrbData3Id4":104002041,"_OrbData4Id4":104002042,"_OrbData5Id4":104003001,"_OrbData1Num4":4,"_OrbData2Num4":1,"_OrbData3Num4":20,"_OrbData4Num4":7,"_OrbData5Num4":2,"_UniqueGrowMaterial1Num4":0,"_UniqueGrowMaterial2Num4":0,"_GrowMaterialNum4":1,"_OrbData1Id5":104001043,"_OrbData2Id5":104001001,"_OrbData3Id5":104002042,"_OrbData4Id5":201014002,"_OrbData5Id5":104003001,"_OrbData1Num5":8,"_OrbData2Num5":16,"_OrbData3Num5":12,"_OrbData4Num5":8,"_OrbData5Num5":2,"_UniqueGrowMaterial1Num5":0,"_UniqueGrowMaterial2Num5":0,"_GrowMaterialNum5":1},{"_Id":1040205,"_OrbData1Id1":104001051,"_OrbData2Id1":0,"_OrbData3Id1":0,"_OrbData4Id1":0,"_OrbData5Id1":0,"_OrbData1Num1":7,"_OrbData2Num1":0,"_OrbData3Num1":0,"_OrbData4Num1":0,"_OrbData5Num1":0,"_UniqueGrowMaterial1Num1":0,"_UniqueGrowMaterial2Num1":0,"_GrowMaterialNum1":1,"_OrbData1Id2":104001051,"_OrbData2Id2":104001052,"_OrbData3Id2":0,"_OrbData4Id2":0,"_OrbData5Id2":0,"_OrbData1Num2":12,"_OrbData2Num2":3,"_OrbData3Num2":0,"_OrbData4Num2":0,"_OrbData5Num2":0,"_UniqueGrowMaterial1Num2":0,"_UniqueGrowMaterial2Num2":0,"_GrowMaterialNum2":1,"_OrbData1Id3":104001052,"_OrbData2Id3":104001053,"_OrbData3Id3":104001001,"_OrbData4Id3":104002051,"_OrbData5Id3":104002052,"_OrbData1Num3":5,"_OrbData2Num3":3,"_OrbData3Num3":1,"_OrbData4Num3":15,"_OrbData5Num3":5,"_UniqueGrowMaterial1Num3":0,"_UniqueGrowMaterial2Num3":0,"_GrowMaterialNum3":1,"_OrbData1Id4":104001053,"_OrbData2Id4":104001001,"_OrbData3Id4":104002051,"_OrbData4Id4":104002052,"_OrbData5Id4":104003001,"_OrbData1Num4":4,"_OrbData2Num4":1,"_OrbData3Num4":20,"_OrbData4Num4":7,"_OrbData5Num4":2,"_UniqueGrowMaterial1Num4":0,"_UniqueGrowMaterial2Num4":0,"_GrowMaterialNum4":1,"_OrbData1Id5":104001053,"_OrbData2Id5":104001001,"_OrbData3Id5":104002052,"_OrbData4Id5":201014002,"_OrbData5Id5":104003001,"_OrbData1Num5":8,"_OrbData2Num5":16,"_OrbData3Num5":12,"_OrbData4Num5":8,"_OrbData5Num5":2,"_UniqueGrowMaterial1Num5":0,"_UniqueGrowMaterial2Num5":0,"_GrowMaterialNum5":1},{"_Id":1040101,"_OrbData1Id1":104001011,"_OrbData2Id1":104001012,"_OrbData3Id1":0,"_OrbData4Id1":0,"_OrbData5Id1":0,"_OrbData1Num1":8,"_OrbData2Num1":1,"_OrbData3Num1":0,"_OrbData4Num1":0,"_OrbData5Num1":0,"_UniqueGrowMaterial1Num1":0,"_UniqueGrowMaterial2Num1":0,"_GrowMaterialNum1":1,"_OrbData1Id2":104001011,"_OrbData2Id2":104001012,"_OrbData3Id2":104001013,"_OrbData4Id2":0,"_OrbData5Id2":0,"_OrbData1Num2":15,"_OrbData2Num2":4,"_OrbData3Num2":1,"_OrbData4Num2":0,"_OrbData5Num2":0,"_UniqueGrowMaterial1Num2":0,"_UniqueGrowMaterial2Num2":0,"_GrowMaterialNum2":1,"_OrbData1Id3":104001012,"_OrbData2Id3":104001013,"_OrbData3Id3":104001001,"_OrbData4Id3":104002011,"_OrbData5Id3":104002012,"_OrbData1Num3":8,"_OrbData2Num3":4,"_OrbData3Num3":1,"_OrbData4Num3":20,"_OrbData5Num3":8,"_UniqueGrowMaterial1Num3":0,"_UniqueGrowMaterial2Num3":0,"_GrowMaterialNum3":1,"_OrbData1Id4":104001013,"_OrbData2Id4":104001001,"_OrbData3Id4":104002011,"_OrbData4Id4":104002012,"_OrbData5Id4":104003001,"_OrbData1Num4":5,"_OrbData2Num4":2,"_OrbData3Num4":25,"_OrbData4Num4":10,"_OrbData5Num4":2,"_UniqueGrowMaterial1Num4":0,"_UniqueGrowMaterial2Num4":0,"_GrowMaterialNum4":1,"_OrbData1Id5":104001013,"_OrbData2Id5":104001001,"_OrbData3Id5":104002012,"_OrbData4Id5":201014002,"_OrbData5Id5":104003001,"_OrbData1Num5":8,"_OrbData2Num5":16,"_OrbData3Num5":12,"_OrbData4Num5":8,"_OrbData5Num5":2,"_UniqueGrowMaterial1Num5":0,"_UniqueGrowMaterial2Num5":0,"_GrowMaterialNum5":1},{"_Id":1040102,"_OrbData1Id1":104001021,"_OrbData2Id1":104001022,"_OrbData3Id1":0,"_OrbData4Id1":0,"_OrbData5Id1":0,"_OrbData1Num1":8,"_OrbData2Num1":1,"_OrbData3Num1":0,"_OrbData4Num1":0,"_OrbData5Num1":0,"_UniqueGrowMaterial1Num1":0,"_UniqueGrowMaterial2Num1":0,"_GrowMaterialNum1":1,"_OrbData1Id2":104001021,"_OrbData2Id2":104001022,"_OrbData3Id2":104001023,"_OrbData4Id2":0,"_OrbData5Id2":0,"_OrbData1Num2":15,"_OrbData2Num2":4,"_OrbData3Num2":1,"_OrbData4Num2":0,"_OrbData5Num2":0,"_UniqueGrowMaterial1Num2":0,"_UniqueGrowMaterial2Num2":0,"_GrowMaterialNum2":1,"_OrbData1Id3":104001022,"_OrbData2Id3":104001023,"_OrbData3Id3":104001001,"_OrbData4Id3":104002021,"_OrbData5Id3":104002022,"_OrbData1Num3":8,"_OrbData2Num3":4,"_OrbData3Num3":1,"_OrbData4Num3":20,"_OrbData5Num3":8,"_UniqueGrowMaterial1Num3":0,"_UniqueGrowMaterial2Num3":0,"_GrowMaterialNum3":1,"_OrbData1Id4":104001023,"_OrbData2Id4":104001001,"_OrbData3Id4":104002021,"_OrbData4Id4":104002022,"_OrbData5Id4":104003001,"_OrbData1Num4":5,"_OrbData2Num4":2,"_OrbData3Num4":25,"_OrbData4Num4":10,"_OrbData5Num4":2,"_UniqueGrowMaterial1Num4":0,"_UniqueGrowMaterial2Num4":0,"_GrowMaterialNum4":1,"_OrbData1Id5":104001023,"_OrbData2Id5":104001001,"_OrbData3Id5":104002022,"_OrbData4Id5":201014002,"_OrbData5Id5":104003001,"_OrbData1Num5":8,"_OrbData2Num5":16,"_OrbData3Num5":12,"_OrbData4Num5":8,"_OrbData5Num5":2,"_UniqueGrowMaterial1Num5":0,"_UniqueGrowMaterial2Num5":0,"_GrowMaterialNum5":1},{"_Id":1040103,"_OrbData1Id1":104001031,"_OrbData2Id1":104001032,"_OrbData3Id1":0,"_OrbData4Id1":0,"_OrbData5Id1":0,"_OrbData1Num1":8,"_OrbData2Num1":1,"_OrbData3Num1":0,"_OrbData4Num1":0,"_OrbData5Num1":0,"_UniqueGrowMaterial1Num1":0,"_UniqueGrowMaterial2Num1":0,"_GrowMaterialNum1":1,"_OrbData1Id2":104001031,"_OrbData2Id2":104001032,"_OrbData3Id2":104001033,"_OrbData4Id2":0,"_OrbData5Id2":0,"_OrbData1Num2":15,"_OrbData2Num2":4,"_OrbData3Num2":1,"_OrbData4Num2":0,"_OrbData5Num2":0,"_UniqueGrowMaterial1Num2":0,"_UniqueGrowMaterial2Num2":0,"_GrowMaterialNum2":1,"_OrbData1Id3":104001032,"_OrbData2Id3":104001033,"_OrbData3Id3":104001001,"_OrbData4Id3":104002031,"_OrbData5Id3":104002032,"_OrbData1Num3":8,"_OrbData2Num3":4,"_OrbData3Num3":1,"_OrbData4Num3":20,"_OrbData5Num3":8,"_UniqueGrowMaterial1Num3":0,"_UniqueGrowMaterial2Num3":0,"_GrowMaterialNum3":1,"_OrbData1Id4":104001033,"_OrbData2Id4":104001001,"_OrbData3Id4":104002031,"_OrbData4Id4":104002032,"_OrbData5Id4":104003001,"_OrbData1Num4":5,"_OrbData2Num4":2,"_OrbData3Num4":25,"_OrbData4Num4":10,"_OrbData5Num4":2,"_UniqueGrowMaterial1Num4":0,"_UniqueGrowMaterial2Num4":0,"_GrowMaterialNum4":1,"_OrbData1Id5":104001033,"_OrbData2Id5":104001001,"_OrbData3Id5":104002032,"_OrbData4Id5":201014002,"_OrbData5Id5":104003001,"_OrbData1Num5":8,"_OrbData2Num5":16,"_OrbData3Num5":12,"_OrbData4Num5":8,"_OrbData5Num5":2,"_UniqueGrowMaterial1Num5":0,"_UniqueGrowMaterial2Num5":0,"_GrowMaterialNum5":1},{"_Id":1040104,"_OrbData1Id1":104001041,"_OrbData2Id1":104001042,"_OrbData3Id1":0,"_OrbData4Id1":0,"_OrbData5Id1":0,"_OrbData1Num1":8,"_OrbData2Num1":1,"_OrbData3Num1":0,"_OrbData4Num1":0,"_OrbData5Num1":0,"_UniqueGrowMaterial1Num1":0,"_UniqueGrowMaterial2Num1":0,"_GrowMaterialNum1":1,"_OrbData1Id2":104001041,"_OrbData2Id2":104001042,"_OrbData3Id2":104001043,"_OrbData4Id2":0,"_OrbData5Id2":0,"_OrbData1Num2":15,"_OrbData2Num2":4,"_OrbData3Num2":1,"_OrbData4Num2":0,"_OrbData5Num2":0,"_UniqueGrowMaterial1Num2":0,"_UniqueGrowMaterial2Num2":0,"_GrowMaterialNum2":1,"_OrbData1Id3":104001042,"_OrbData2Id3":104001043,"_OrbData3Id3":104001001,"_OrbData4Id3":104002041,"_OrbData5Id3":104002042,"_OrbData1Num3":8,"_OrbData2Num3":4,"_OrbData3Num3":1,"_OrbData4Num3":20,"_OrbData5Num3":8,"_UniqueGrowMaterial1Num3":0,"_UniqueGrowMaterial2Num3":0,"_GrowMaterialNum3":1,"_OrbData1Id4":104001043,"_OrbData2Id4":104001001,"_OrbData3Id4":104002041,"_OrbData4Id4":104002042,"_OrbData5Id4":104003001,"_OrbData1Num4":5,"_OrbData2Num4":2,"_OrbData3Num4":25,"_OrbData4Num4":10,"_OrbData5Num4":2,"_UniqueGrowMaterial1Num4":0,"_UniqueGrowMaterial2Num4":0,"_GrowMaterialNum4":1,"_OrbData1Id5":104001043,"_OrbData2Id5":104001001,"_OrbData3Id5":104002042,"_OrbData4Id5":201014002,"_OrbData5Id5":104003001,"_OrbData1Num5":8,"_OrbData2Num5":16,"_OrbData3Num5":12,"_OrbData4Num5":8,"_OrbData5Num5":2,"_UniqueGrowMaterial1Num5":0,"_UniqueGrowMaterial2Num5":0,"_GrowMaterialNum5":1},{"_Id":1040105,"_OrbData1Id1":104001051,"_OrbData2Id1":104001052,"_OrbData3Id1":0,"_OrbData4Id1":0,"_OrbData5Id1":0,"_OrbData1Num1":8,"_OrbData2Num1":1,"_OrbData3Num1":0,"_OrbData4Num1":0,"_OrbData5Num1":0,"_UniqueGrowMaterial1Num1":0,"_UniqueGrowMaterial2Num1":0,"_GrowMaterialNum1":1,"_OrbData1Id2":104001051,"_OrbData2Id2":104001052,"_OrbData3Id2":104001053,"_OrbData4Id2":0,"_OrbData5Id2":0,"_OrbData1Num2":15,"_OrbData2Num2":4,"_OrbData3Num2":1,"_OrbData4Num2":0,"_OrbData5Num2":0,"_UniqueGrowMaterial1Num2":0,"_UniqueGrowMaterial2Num2":0,"_GrowMaterialNum2":1,"_OrbData1Id3":104001052,"_OrbData2Id3":104001053,"_OrbData3Id3":104001001,"_OrbData4Id3":104002051,"_OrbData5Id3":104002052,"_OrbData1Num3":8,"_OrbData2Num3":4,"_OrbData3Num3":1,"_OrbData4Num3":20,"_OrbData5Num3":8,"_UniqueGrowMaterial1Num3":0,"_UniqueGrowMaterial2Num3":0,"_GrowMaterialNum3":1,"_OrbData1Id4":104001053,"_OrbData2Id4":104001001,"_OrbData3Id4":104002051,"_OrbData4Id4":104002052,"_OrbData5Id4":104003001,"_OrbData1Num4":5,"_OrbData2Num4":2,"_OrbData3Num4":25,"_OrbData4Num4":10,"_OrbData5Num4":2,"_UniqueGrowMaterial1Num4":0,"_UniqueGrowMaterial2Num4":0,"_GrowMaterialNum4":1,"_OrbData1Id5":104001053,"_OrbData2Id5":104001001,"_OrbData3Id5":104002052,"_OrbData4Id5":201014002,"_OrbData5Id5":104003001,"_OrbData1Num5":8,"_OrbData2Num5":16,"_OrbData3Num5":12,"_OrbData4Num5":8,"_OrbData5Num5":2,"_UniqueGrowMaterial1Num5":0,"_UniqueGrowMaterial2Num5":0,"_GrowMaterialNum5":1},{"_Id":1040301,"_OrbData1Id1":104001011,"_OrbData2Id1":104001012,"_OrbData3Id1":0,"_OrbData4Id1":0,"_OrbData5Id1":0,"_OrbData1Num1":8,"_OrbData2Num1":1,"_OrbData3Num1":0,"_OrbData4Num1":0,"_OrbData5Num1":0,"_UniqueGrowMaterial1Num1":0,"_UniqueGrowMaterial2Num1":0,"_GrowMaterialNum1":1,"_OrbData1Id2":104001011,"_OrbData2Id2":104001012,"_OrbData3Id2":104001013,"_OrbData4Id2":0,"_OrbData5Id2":0,"_OrbData1Num2":15,"_OrbData2Num2":4,"_OrbData3Num2":1,"_OrbData4Num2":0,"_OrbData5Num2":0,"_UniqueGrowMaterial1Num2":0,"_UniqueGrowMaterial2Num2":0,"_GrowMaterialNum2":1,"_OrbData1Id3":104001012,"_OrbData2Id3":104001013,"_OrbData3Id3":104001001,"_OrbData4Id3":104002011,"_OrbData5Id3":104002012,"_OrbData1Num3":8,"_OrbData2Num3":4,"_OrbData3Num3":1,"_OrbData4Num3":20,"_OrbData5Num3":8,"_UniqueGrowMaterial1Num3":0,"_UniqueGrowMaterial2Num3":0,"_GrowMaterialNum3":1,"_OrbData1Id4":104001013,"_OrbData2Id4":104001001,"_OrbData3Id4":104002011,"_OrbData4Id4":104002012,"_OrbData5Id4":104003001,"_OrbData1Num4":5,"_OrbData2Num4":2,"_OrbData3Num4":25,"_OrbData4Num4":10,"_OrbData5Num4":2,"_UniqueGrowMaterial1Num4":0,"_UniqueGrowMaterial2Num4":0,"_GrowMaterialNum4":1,"_OrbData1Id5":0,"_OrbData2Id5":0,"_OrbData3Id5":0,"_OrbData4Id5":0,"_OrbData5Id5":0,"_OrbData1Num5":0,"_OrbData2Num5":0,"_OrbData3Num5":0,"_OrbData4Num5":0,"_OrbData5Num5":0,"_UniqueGrowMaterial1Num5":1,"_UniqueGrowMaterial2Num5":0,"_GrowMaterialNum5":1},{"_Id":1040302,"_OrbData1Id1":104001021,"_OrbData2Id1":104001022,"_OrbData3Id1":0,"_OrbData4Id1":0,"_OrbData5Id1":0,"_OrbData1Num1":8,"_OrbData2Num1":1,"_OrbData3Num1":0,"_OrbData4Num1":0,"_OrbData5Num1":0,"_UniqueGrowMaterial1Num1":0,"_UniqueGrowMaterial2Num1":0,"_GrowMaterialNum1":1,"_OrbData1Id2":104001021,"_OrbData2Id2":104001022,"_OrbData3Id2":104001023,"_OrbData4Id2":0,"_OrbData5Id2":0,"_OrbData1Num2":15,"_OrbData2Num2":4,"_OrbData3Num2":1,"_OrbData4Num2":0,"_OrbData5Num2":0,"_UniqueGrowMaterial1Num2":0,"_UniqueGrowMaterial2Num2":0,"_GrowMaterialNum2":1,"_OrbData1Id3":104001022,"_OrbData2Id3":104001023,"_OrbData3Id3":104001001,"_OrbData4Id3":104002021,"_OrbData5Id3":104002022,"_OrbData1Num3":8,"_OrbData2Num3":4,"_OrbData3Num3":1,"_OrbData4Num3":20,"_OrbData5Num3":8,"_UniqueGrowMaterial1Num3":0,"_UniqueGrowMaterial2Num3":0,"_GrowMaterialNum3":1,"_OrbData1Id4":104001023,"_OrbData2Id4":104001001,"_OrbData3Id4":104002021,"_OrbData4Id4":104002022,"_OrbData5Id4":104003001,"_OrbData1Num4":5,"_OrbData2Num4":2,"_OrbData3Num4":25,"_OrbData4Num4":10,"_OrbData5Num4":2,"_UniqueGrowMaterial1Num4":0,"_UniqueGrowMaterial2Num4":0,"_GrowMaterialNum4":1,"_OrbData1Id5":0,"_OrbData2Id5":0,"_OrbData3Id5":0,"_OrbData4Id5":0,"_OrbData5Id5":0,"_OrbData1Num5":0,"_OrbData2Num5":0,"_OrbData3Num5":0,"_OrbData4Num5":0,"_OrbData5Num5":0,"_UniqueGrowMaterial1Num5":1,"_UniqueGrowMaterial2Num5":0,"_GrowMaterialNum5":1},{"_Id":1040303,"_OrbData1Id1":104001031,"_OrbData2Id1":104001032,"_OrbData3Id1":0,"_OrbData4Id1":0,"_OrbData5Id1":0,"_OrbData1Num1":8,"_OrbData2Num1":1,"_OrbData3Num1":0,"_OrbData4Num1":0,"_OrbData5Num1":0,"_UniqueGrowMaterial1Num1":0,"_UniqueGrowMaterial2Num1":0,"_GrowMaterialNum1":1,"_OrbData1Id2":104001031,"_OrbData2Id2":104001032,"_OrbData3Id2":104001033,"_OrbData4Id2":0,"_OrbData5Id2":0,"_OrbData1Num2":15,"_OrbData2Num2":4,"_OrbData3Num2":1,"_OrbData4Num2":0,"_OrbData5Num2":0,"_UniqueGrowMaterial1Num2":0,"_UniqueGrowMaterial2Num2":0,"_GrowMaterialNum2":1,"_OrbData1Id3":104001032,"_OrbData2Id3":104001033,"_OrbData3Id3":104001001,"_OrbData4Id3":104002031,"_OrbData5Id3":104002032,"_OrbData1Num3":8,"_OrbData2Num3":4,"_OrbData3Num3":1,"_OrbData4Num3":20,"_OrbData5Num3":8,"_UniqueGrowMaterial1Num3":0,"_UniqueGrowMaterial2Num3":0,"_GrowMaterialNum3":1,"_OrbData1Id4":104001033,"_OrbData2Id4":104001001,"_OrbData3Id4":104002031,"_OrbData4Id4":104002032,"_OrbData5Id4":104003001,"_OrbData1Num4":5,"_OrbData2Num4":2,"_OrbData3Num4":25,"_OrbData4Num4":10,"_OrbData5Num4":2,"_UniqueGrowMaterial1Num4":0,"_UniqueGrowMaterial2Num4":0,"_GrowMaterialNum4":1,"_OrbData1Id5":0,"_OrbData2Id5":0,"_OrbData3Id5":0,"_OrbData4Id5":0,"_OrbData5Id5":0,"_OrbData1Num5":0,"_OrbData2Num5":0,"_OrbData3Num5":0,"_OrbData4Num5":0,"_OrbData5Num5":0,"_UniqueGrowMaterial1Num5":1,"_UniqueGrowMaterial2Num5":0,"_GrowMaterialNum5":1},{"_Id":1040304,"_OrbData1Id1":104001041,"_OrbData2Id1":104001042,"_OrbData3Id1":0,"_OrbData4Id1":0,"_OrbData5Id1":0,"_OrbData1Num1":8,"_OrbData2Num1":1,"_OrbData3Num1":0,"_OrbData4Num1":0,"_OrbData5Num1":0,"_UniqueGrowMaterial1Num1":0,"_UniqueGrowMaterial2Num1":0,"_GrowMaterialNum1":1,"_OrbData1Id2":104001041,"_OrbData2Id2":104001042,"_OrbData3Id2":104001043,"_OrbData4Id2":0,"_OrbData5Id2":0,"_OrbData1Num2":15,"_OrbData2Num2":4,"_OrbData3Num2":1,"_OrbData4Num2":0,"_OrbData5Num2":0,"_UniqueGrowMaterial1Num2":0,"_UniqueGrowMaterial2Num2":0,"_GrowMaterialNum2":1,"_OrbData1Id3":104001042,"_OrbData2Id3":104001043,"_OrbData3Id3":104001001,"_OrbData4Id3":104002041,"_OrbData5Id3":104002042,"_OrbData1Num3":8,"_OrbData2Num3":4,"_OrbData3Num3":1,"_OrbData4Num3":20,"_OrbData5Num3":8,"_UniqueGrowMaterial1Num3":0,"_UniqueGrowMaterial2Num3":0,"_GrowMaterialNum3":1,"_OrbData1Id4":104001043,"_OrbData2Id4":104001001,"_OrbData3Id4":104002041,"_OrbData4Id4":104002042,"_OrbData5Id4":104003001,"_OrbData1Num4":5,"_OrbData2Num4":2,"_OrbData3Num4":25,"_OrbData4Num4":10,"_OrbData5Num4":2,"_UniqueGrowMaterial1Num4":0,"_UniqueGrowMaterial2Num4":0,"_GrowMaterialNum4":1,"_OrbData1Id5":0,"_OrbData2Id5":0,"_OrbData3Id5":0,"_OrbData4Id5":0,"_OrbData5Id5":0,"_OrbData1Num5":0,"_OrbData2Num5":0,"_OrbData3Num5":0,"_OrbData4Num5":0,"_OrbData5Num5":0,"_UniqueGrowMaterial1Num5":1,"_UniqueGrowMaterial2Num5":0,"_GrowMaterialNum5":1},{"_Id":1040305,"_OrbData1Id1":104001051,"_OrbData2Id1":104001052,"_OrbData3Id1":0,"_OrbData4Id1":0,"_OrbData5Id1":0,"_OrbData1Num1":8,"_OrbData2Num1":1,"_OrbData3Num1":0,"_OrbData4Num1":0,"_OrbData5Num1":0,"_UniqueGrowMaterial1Num1":0,"_UniqueGrowMaterial2Num1":0,"_GrowMaterialNum1":1,"_OrbData1Id2":104001051,"_OrbData2Id2":104001052,"_OrbData3Id2":104001053,"_OrbData4Id2":0,"_OrbData5Id2":0,"_OrbData1Num2":15,"_OrbData2Num2":4,"_OrbData3Num2":1,"_OrbData4Num2":0,"_OrbData5Num2":0,"_UniqueGrowMaterial1Num2":0,"_UniqueGrowMaterial2Num2":0,"_GrowMaterialNum2":1,"_OrbData1Id3":104001052,"_OrbData2Id3":104001053,"_OrbData3Id3":104001001,"_OrbData4Id3":104002051,"_OrbData5Id3":104002052,"_OrbData1Num3":8,"_OrbData2Num3":4,"_OrbData3Num3":1,"_OrbData4Num3":20,"_OrbData5Num3":8,"_UniqueGrowMaterial1Num3":0,"_UniqueGrowMaterial2Num3":0,"_GrowMaterialNum3":1,"_OrbData1Id4":104001053,"_OrbData2Id4":104001001,"_OrbData3Id4":104002051,"_OrbData4Id4":104002052,"_OrbData5Id4":104003001,"_OrbData1Num4":5,"_OrbData2Num4":2,"_OrbData3Num4":25,"_OrbData4Num4":10,"_OrbData5Num4":2,"_UniqueGrowMaterial1Num4":0,"_UniqueGrowMaterial2Num4":0,"_GrowMaterialNum4":1,"_OrbData1Id5":0,"_OrbData2Id5":0,"_OrbData3Id5":0,"_OrbData4Id5":0,"_OrbData5Id5":0,"_OrbData1Num5":0,"_OrbData2Num5":0,"_OrbData3Num5":0,"_OrbData4Num5":0,"_OrbData5Num5":0,"_UniqueGrowMaterial1Num5":1,"_UniqueGrowMaterial2Num5":0,"_GrowMaterialNum5":1},{"_Id":1050101,"_OrbData1Id1":104001011,"_OrbData2Id1":104001012,"_OrbData3Id1":0,"_OrbData4Id1":0,"_OrbData5Id1":0,"_OrbData1Num1":10,"_OrbData2Num1":1,"_OrbData3Num1":0,"_OrbData4Num1":0,"_OrbData5Num1":0,"_UniqueGrowMaterial1Num1":0,"_UniqueGrowMaterial2Num1":0,"_GrowMaterialNum1":1,"_OrbData1Id2":104001011,"_OrbData2Id2":104001012,"_OrbData3Id2":104001013,"_OrbData4Id2":0,"_OrbData5Id2":0,"_OrbData1Num2":20,"_OrbData2Num2":5,"_OrbData3Num2":1,"_OrbData4Num2":0,"_OrbData5Num2":0,"_UniqueGrowMaterial1Num2":0,"_UniqueGrowMaterial2Num2":0,"_GrowMaterialNum2":1,"_OrbData1Id3":104001012,"_OrbData2Id3":104001013,"_OrbData3Id3":104001001,"_OrbData4Id3":104002011,"_OrbData5Id3":104002012,"_OrbData1Num3":10,"_OrbData2Num3":5,"_OrbData3Num3":1,"_OrbData4Num3":25,"_OrbData5Num3":10,"_UniqueGrowMaterial1Num3":0,"_UniqueGrowMaterial2Num3":0,"_GrowMaterialNum3":1,"_OrbData1Id4":104001013,"_OrbData2Id4":104001001,"_OrbData3Id4":104002011,"_OrbData4Id4":104002012,"_OrbData5Id4":104003002,"_OrbData1Num4":7,"_OrbData2Num4":3,"_OrbData3Num4":30,"_OrbData4Num4":12,"_OrbData5Num4":1,"_UniqueGrowMaterial1Num4":0,"_UniqueGrowMaterial2Num4":0,"_GrowMaterialNum4":1,"_OrbData1Id5":104001013,"_OrbData2Id5":104001001,"_OrbData3Id5":104002012,"_OrbData4Id5":201014002,"_OrbData5Id5":104003002,"_OrbData1Num5":10,"_OrbData2Num5":20,"_OrbData3Num5":15,"_OrbData4Num5":3,"_OrbData5Num5":1,"_UniqueGrowMaterial1Num5":0,"_UniqueGrowMaterial2Num5":0,"_GrowMaterialNum5":1},{"_Id":1050102,"_OrbData1Id1":104001021,"_OrbData2Id1":104001022,"_OrbData3Id1":0,"_OrbData4Id1":0,"_OrbData5Id1":0,"_OrbData1Num1":10,"_OrbData2Num1":1,"_OrbData3Num1":0,"_OrbData4Num1":0,"_OrbData5Num1":0,"_UniqueGrowMaterial1Num1":0,"_UniqueGrowMaterial2Num1":0,"_GrowMaterialNum1":1,"_OrbData1Id2":104001021,"_OrbData2Id2":104001022,"_OrbData3Id2":104001023,"_OrbData4Id2":0,"_OrbData5Id2":0,"_OrbData1Num2":20,"_OrbData2Num2":5,"_OrbData3Num2":1,"_OrbData4Num2":0,"_OrbData5Num2":0,"_UniqueGrowMaterial1Num2":0,"_UniqueGrowMaterial2Num2":0,"_GrowMaterialNum2":1,"_OrbData1Id3":104001022,"_OrbData2Id3":104001023,"_OrbData3Id3":104001001,"_OrbData4Id3":104002021,"_OrbData5Id3":104002022,"_OrbData1Num3":10,"_OrbData2Num3":5,"_OrbData3Num3":1,"_OrbData4Num3":25,"_OrbData5Num3":10,"_UniqueGrowMaterial1Num3":0,"_UniqueGrowMaterial2Num3":0,"_GrowMaterialNum3":1,"_OrbData1Id4":104001023,"_OrbData2Id4":104001001,"_OrbData3Id4":104002021,"_OrbData4Id4":104002022,"_OrbData5Id4":104003002,"_OrbData1Num4":7,"_OrbData2Num4":3,"_OrbData3Num4":30,"_OrbData4Num4":12,"_OrbData5Num4":1,"_UniqueGrowMaterial1Num4":0,"_UniqueGrowMaterial2Num4":0,"_GrowMaterialNum4":1,"_OrbData1Id5":104001023,"_OrbData2Id5":104001001,"_OrbData3Id5":104002022,"_OrbData4Id5":201014002,"_OrbData5Id5":104003002,"_OrbData1Num5":10,"_OrbData2Num5":20,"_OrbData3Num5":15,"_OrbData4Num5":3,"_OrbData5Num5":1,"_UniqueGrowMaterial1Num5":0,"_UniqueGrowMaterial2Num5":0,"_GrowMaterialNum5":1},{"_Id":1050103,"_OrbData1Id1":104001031,"_OrbData2Id1":104001032,"_OrbData3Id1":0,"_OrbData4Id1":0,"_OrbData5Id1":0,"_OrbData1Num1":10,"_OrbData2Num1":1,"_OrbData3Num1":0,"_OrbData4Num1":0,"_OrbData5Num1":0,"_UniqueGrowMaterial1Num1":0,"_UniqueGrowMaterial2Num1":0,"_GrowMaterialNum1":1,"_OrbData1Id2":104001031,"_OrbData2Id2":104001032,"_OrbData3Id2":104001033,"_OrbData4Id2":0,"_OrbData5Id2":0,"_OrbData1Num2":20,"_OrbData2Num2":5,"_OrbData3Num2":1,"_OrbData4Num2":0,"_OrbData5Num2":0,"_UniqueGrowMaterial1Num2":0,"_UniqueGrowMaterial2Num2":0,"_GrowMaterialNum2":1,"_OrbData1Id3":104001032,"_OrbData2Id3":104001033,"_OrbData3Id3":104001001,"_OrbData4Id3":104002031,"_OrbData5Id3":104002032,"_OrbData1Num3":10,"_OrbData2Num3":5,"_OrbData3Num3":1,"_OrbData4Num3":25,"_OrbData5Num3":10,"_UniqueGrowMaterial1Num3":0,"_UniqueGrowMaterial2Num3":0,"_GrowMaterialNum3":1,"_OrbData1Id4":104001033,"_OrbData2Id4":104001001,"_OrbData3Id4":104002031,"_OrbData4Id4":104002032,"_OrbData5Id4":104003002,"_OrbData1Num4":7,"_OrbData2Num4":3,"_OrbData3Num4":30,"_OrbData4Num4":12,"_OrbData5Num4":1,"_UniqueGrowMaterial1Num4":0,"_UniqueGrowMaterial2Num4":0,"_GrowMaterialNum4":1,"_OrbData1Id5":104001033,"_OrbData2Id5":104001001,"_OrbData3Id5":104002032,"_OrbData4Id5":201014002,"_OrbData5Id5":104003002,"_OrbData1Num5":10,"_OrbData2Num5":20,"_OrbData3Num5":15,"_OrbData4Num5":3,"_OrbData5Num5":1,"_UniqueGrowMaterial1Num5":0,"_UniqueGrowMaterial2Num5":0,"_GrowMaterialNum5":1},{"_Id":1050104,"_OrbData1Id1":104001041,"_OrbData2Id1":104001042,"_OrbData3Id1":0,"_OrbData4Id1":0,"_OrbData5Id1":0,"_OrbData1Num1":10,"_OrbData2Num1":1,"_OrbData3Num1":0,"_OrbData4Num1":0,"_OrbData5Num1":0,"_UniqueGrowMaterial1Num1":0,"_UniqueGrowMaterial2Num1":0,"_GrowMaterialNum1":1,"_OrbData1Id2":104001041,"_OrbData2Id2":104001042,"_OrbData3Id2":104001043,"_OrbData4Id2":0,"_OrbData5Id2":0,"_OrbData1Num2":20,"_OrbData2Num2":5,"_OrbData3Num2":1,"_OrbData4Num2":0,"_OrbData5Num2":0,"_UniqueGrowMaterial1Num2":0,"_UniqueGrowMaterial2Num2":0,"_GrowMaterialNum2":1,"_OrbData1Id3":104001042,"_OrbData2Id3":104001043,"_OrbData3Id3":104001001,"_OrbData4Id3":104002041,"_OrbData5Id3":104002042,"_OrbData1Num3":10,"_OrbData2Num3":5,"_OrbData3Num3":1,"_OrbData4Num3":25,"_OrbData5Num3":10,"_UniqueGrowMaterial1Num3":0,"_UniqueGrowMaterial2Num3":0,"_GrowMaterialNum3":1,"_OrbData1Id4":104001043,"_OrbData2Id4":104001001,"_OrbData3Id4":104002041,"_OrbData4Id4":104002042,"_OrbData5Id4":104003002,"_OrbData1Num4":7,"_OrbData2Num4":3,"_OrbData3Num4":30,"_OrbData4Num4":12,"_OrbData5Num4":1,"_UniqueGrowMaterial1Num4":0,"_UniqueGrowMaterial2Num4":0,"_GrowMaterialNum4":1,"_OrbData1Id5":104001043,"_OrbData2Id5":104001001,"_OrbData3Id5":104002042,"_OrbData4Id5":201014002,"_OrbData5Id5":104003002,"_OrbData1Num5":10,"_OrbData2Num5":20,"_OrbData3Num5":15,"_OrbData4Num5":3,"_OrbData5Num5":1,"_UniqueGrowMaterial1Num5":0,"_UniqueGrowMaterial2Num5":0,"_GrowMaterialNum5":1},{"_Id":1050105,"_OrbData1Id1":104001051,"_OrbData2Id1":104001052,"_OrbData3Id1":0,"_OrbData4Id1":0,"_OrbData5Id1":0,"_OrbData1Num1":10,"_OrbData2Num1":1,"_OrbData3Num1":0,"_OrbData4Num1":0,"_OrbData5Num1":0,"_UniqueGrowMaterial1Num1":0,"_UniqueGrowMaterial2Num1":0,"_GrowMaterialNum1":1,"_OrbData1Id2":104001051,"_OrbData2Id2":104001052,"_OrbData3Id2":104001053,"_OrbData4Id2":0,"_OrbData5Id2":0,"_OrbData1Num2":20,"_OrbData2Num2":5,"_OrbData3Num2":1,"_OrbData4Num2":0,"_OrbData5Num2":0,"_UniqueGrowMaterial1Num2":0,"_UniqueGrowMaterial2Num2":0,"_GrowMaterialNum2":1,"_OrbData1Id3":104001052,"_OrbData2Id3":104001053,"_OrbData3Id3":104001001,"_OrbData4Id3":104002051,"_OrbData5Id3":104002052,"_OrbData1Num3":10,"_OrbData2Num3":5,"_OrbData3Num3":1,"_OrbData4Num3":25,"_OrbData5Num3":10,"_UniqueGrowMaterial1Num3":0,"_UniqueGrowMaterial2Num3":0,"_GrowMaterialNum3":1,"_OrbData1Id4":104001053,"_OrbData2Id4":104001001,"_OrbData3Id4":104002051,"_OrbData4Id4":104002052,"_OrbData5Id4":104003002,"_OrbData1Num4":7,"_OrbData2Num4":3,"_OrbData3Num4":30,"_OrbData4Num4":12,"_OrbData5Num4":1,"_UniqueGrowMaterial1Num4":0,"_UniqueGrowMaterial2Num4":0,"_GrowMaterialNum4":1,"_OrbData1Id5":104001053,"_OrbData2Id5":104001001,"_OrbData3Id5":104002052,"_OrbData4Id5":201014002,"_OrbData5Id5":104003002,"_OrbData1Num5":10,"_OrbData2Num5":20,"_OrbData3Num5":15,"_OrbData4Num5":3,"_OrbData5Num5":1,"_UniqueGrowMaterial1Num5":0,"_UniqueGrowMaterial2Num5":0,"_GrowMaterialNum5":1},{"_Id":1050201,"_OrbData1Id1":104001011,"_OrbData2Id1":104001012,"_OrbData3Id1":0,"_OrbData4Id1":0,"_OrbData5Id1":0,"_OrbData1Num1":10,"_OrbData2Num1":1,"_OrbData3Num1":0,"_OrbData4Num1":0,"_OrbData5Num1":0,"_UniqueGrowMaterial1Num1":0,"_UniqueGrowMaterial2Num1":0,"_GrowMaterialNum1":1,"_OrbData1Id2":104001011,"_OrbData2Id2":104001012,"_OrbData3Id2":104001013,"_OrbData4Id2":0,"_OrbData5Id2":0,"_OrbData1Num2":20,"_OrbData2Num2":5,"_OrbData3Num2":1,"_OrbData4Num2":0,"_OrbData5Num2":0,"_UniqueGrowMaterial1Num2":0,"_UniqueGrowMaterial2Num2":0,"_GrowMaterialNum2":1,"_OrbData1Id3":104001012,"_OrbData2Id3":104001013,"_OrbData3Id3":104001001,"_OrbData4Id3":104002011,"_OrbData5Id3":104002012,"_OrbData1Num3":10,"_OrbData2Num3":5,"_OrbData3Num3":1,"_OrbData4Num3":25,"_OrbData5Num3":10,"_UniqueGrowMaterial1Num3":0,"_UniqueGrowMaterial2Num3":0,"_GrowMaterialNum3":1,"_OrbData1Id4":104001013,"_OrbData2Id4":104001001,"_OrbData3Id4":104002011,"_OrbData4Id4":104002012,"_OrbData5Id4":104003002,"_OrbData1Num4":7,"_OrbData2Num4":3,"_OrbData3Num4":30,"_OrbData4Num4":12,"_OrbData5Num4":1,"_UniqueGrowMaterial1Num4":0,"_UniqueGrowMaterial2Num4":0,"_GrowMaterialNum4":1,"_OrbData1Id5":0,"_OrbData2Id5":0,"_OrbData3Id5":0,"_OrbData4Id5":0,"_OrbData5Id5":0,"_OrbData1Num5":0,"_OrbData2Num5":0,"_OrbData3Num5":0,"_OrbData4Num5":0,"_OrbData5Num5":0,"_UniqueGrowMaterial1Num5":1,"_UniqueGrowMaterial2Num5":0,"_GrowMaterialNum5":1},{"_Id":1050202,"_OrbData1Id1":104001021,"_OrbData2Id1":104001022,"_OrbData3Id1":0,"_OrbData4Id1":0,"_OrbData5Id1":0,"_OrbData1Num1":10,"_OrbData2Num1":1,"_OrbData3Num1":0,"_OrbData4Num1":0,"_OrbData5Num1":0,"_UniqueGrowMaterial1Num1":0,"_UniqueGrowMaterial2Num1":0,"_GrowMaterialNum1":1,"_OrbData1Id2":104001021,"_OrbData2Id2":104001022,"_OrbData3Id2":104001023,"_OrbData4Id2":0,"_OrbData5Id2":0,"_OrbData1Num2":20,"_OrbData2Num2":5,"_OrbData3Num2":1,"_OrbData4Num2":0,"_OrbData5Num2":0,"_UniqueGrowMaterial1Num2":0,"_UniqueGrowMaterial2Num2":0,"_GrowMaterialNum2":1,"_OrbData1Id3":104001022,"_OrbData2Id3":104001023,"_OrbData3Id3":104001001,"_OrbData4Id3":104002021,"_OrbData5Id3":104002022,"_OrbData1Num3":10,"_OrbData2Num3":5,"_OrbData3Num3":1,"_OrbData4Num3":25,"_OrbData5Num3":10,"_UniqueGrowMaterial1Num3":0,"_UniqueGrowMaterial2Num3":0,"_GrowMaterialNum3":1,"_OrbData1Id4":104001023,"_OrbData2Id4":104001001,"_OrbData3Id4":104002021,"_OrbData4Id4":104002022,"_OrbData5Id4":104003002,"_OrbData1Num4":7,"_OrbData2Num4":3,"_OrbData3Num4":30,"_OrbData4Num4":12,"_OrbData5Num4":1,"_UniqueGrowMaterial1Num4":0,"_UniqueGrowMaterial2Num4":0,"_GrowMaterialNum4":1,"_OrbData1Id5":0,"_OrbData2Id5":0,"_OrbData3Id5":0,"_OrbData4Id5":0,"_OrbData5Id5":0,"_OrbData1Num5":0,"_OrbData2Num5":0,"_OrbData3Num5":0,"_OrbData4Num5":0,"_OrbData5Num5":0,"_UniqueGrowMaterial1Num5":1,"_UniqueGrowMaterial2Num5":0,"_GrowMaterialNum5":1},{"_Id":1050203,"_OrbData1Id1":104001031,"_OrbData2Id1":104001032,"_OrbData3Id1":0,"_OrbData4Id1":0,"_OrbData5Id1":0,"_OrbData1Num1":10,"_OrbData2Num1":1,"_OrbData3Num1":0,"_OrbData4Num1":0,"_OrbData5Num1":0,"_UniqueGrowMaterial1Num1":0,"_UniqueGrowMaterial2Num1":0,"_GrowMaterialNum1":1,"_OrbData1Id2":104001031,"_OrbData2Id2":104001032,"_OrbData3Id2":104001033,"_OrbData4Id2":0,"_OrbData5Id2":0,"_OrbData1Num2":20,"_OrbData2Num2":5,"_OrbData3Num2":1,"_OrbData4Num2":0,"_OrbData5Num2":0,"_UniqueGrowMaterial1Num2":0,"_UniqueGrowMaterial2Num2":0,"_GrowMaterialNum2":1,"_OrbData1Id3":104001032,"_OrbData2Id3":104001033,"_OrbData3Id3":104001001,"_OrbData4Id3":104002031,"_OrbData5Id3":104002032,"_OrbData1Num3":10,"_OrbData2Num3":5,"_OrbData3Num3":1,"_OrbData4Num3":25,"_OrbData5Num3":10,"_UniqueGrowMaterial1Num3":0,"_UniqueGrowMaterial2Num3":0,"_GrowMaterialNum3":1,"_OrbData1Id4":104001033,"_OrbData2Id4":104001001,"_OrbData3Id4":104002031,"_OrbData4Id4":104002032,"_OrbData5Id4":104003002,"_OrbData1Num4":7,"_OrbData2Num4":3,"_OrbData3Num4":30,"_OrbData4Num4":12,"_OrbData5Num4":1,"_UniqueGrowMaterial1Num4":0,"_UniqueGrowMaterial2Num4":0,"_GrowMaterialNum4":1,"_OrbData1Id5":0,"_OrbData2Id5":0,"_OrbData3Id5":0,"_OrbData4Id5":0,"_OrbData5Id5":0,"_OrbData1Num5":0,"_OrbData2Num5":0,"_OrbData3Num5":0,"_OrbData4Num5":0,"_OrbData5Num5":0,"_UniqueGrowMaterial1Num5":1,"_UniqueGrowMaterial2Num5":0,"_GrowMaterialNum5":1},{"_Id":1050204,"_OrbData1Id1":104001041,"_OrbData2Id1":104001042,"_OrbData3Id1":0,"_OrbData4Id1":0,"_OrbData5Id1":0,"_OrbData1Num1":10,"_OrbData2Num1":1,"_OrbData3Num1":0,"_OrbData4Num1":0,"_OrbData5Num1":0,"_UniqueGrowMaterial1Num1":0,"_UniqueGrowMaterial2Num1":0,"_GrowMaterialNum1":1,"_OrbData1Id2":104001041,"_OrbData2Id2":104001042,"_OrbData3Id2":104001043,"_OrbData4Id2":0,"_OrbData5Id2":0,"_OrbData1Num2":20,"_OrbData2Num2":5,"_OrbData3Num2":1,"_OrbData4Num2":0,"_OrbData5Num2":0,"_UniqueGrowMaterial1Num2":0,"_UniqueGrowMaterial2Num2":0,"_GrowMaterialNum2":1,"_OrbData1Id3":104001042,"_OrbData2Id3":104001043,"_OrbData3Id3":104001001,"_OrbData4Id3":104002041,"_OrbData5Id3":104002042,"_OrbData1Num3":10,"_OrbData2Num3":5,"_OrbData3Num3":1,"_OrbData4Num3":25,"_OrbData5Num3":10,"_UniqueGrowMaterial1Num3":0,"_UniqueGrowMaterial2Num3":0,"_GrowMaterialNum3":1,"_OrbData1Id4":104001043,"_OrbData2Id4":104001001,"_OrbData3Id4":104002041,"_OrbData4Id4":104002042,"_OrbData5Id4":104003002,"_OrbData1Num4":7,"_OrbData2Num4":3,"_OrbData3Num4":30,"_OrbData4Num4":12,"_OrbData5Num4":1,"_UniqueGrowMaterial1Num4":0,"_UniqueGrowMaterial2Num4":0,"_GrowMaterialNum4":1,"_OrbData1Id5":0,"_OrbData2Id5":0,"_OrbData3Id5":0,"_OrbData4Id5":0,"_OrbData5Id5":0,"_OrbData1Num5":0,"_OrbData2Num5":0,"_OrbData3Num5":0,"_OrbData4Num5":0,"_OrbData5Num5":0,"_UniqueGrowMaterial1Num5":1,"_UniqueGrowMaterial2Num5":0,"_GrowMaterialNum5":1},{"_Id":1050205,"_OrbData1Id1":104001051,"_OrbData2Id1":104001052,"_OrbData3Id1":0,"_OrbData4Id1":0,"_OrbData5Id1":0,"_OrbData1Num1":10,"_OrbData2Num1":1,"_OrbData3Num1":0,"_OrbData4Num1":0,"_OrbData5Num1":0,"_UniqueGrowMaterial1Num1":0,"_UniqueGrowMaterial2Num1":0,"_GrowMaterialNum1":1,"_OrbData1Id2":104001051,"_OrbData2Id2":104001052,"_OrbData3Id2":104001053,"_OrbData4Id2":0,"_OrbData5Id2":0,"_OrbData1Num2":20,"_OrbData2Num2":5,"_OrbData3Num2":1,"_OrbData4Num2":0,"_OrbData5Num2":0,"_UniqueGrowMaterial1Num2":0,"_UniqueGrowMaterial2Num2":0,"_GrowMaterialNum2":1,"_OrbData1Id3":104001052,"_OrbData2Id3":104001053,"_OrbData3Id3":104001001,"_OrbData4Id3":104002051,"_OrbData5Id3":104002052,"_OrbData1Num3":10,"_OrbData2Num3":5,"_OrbData3Num3":1,"_OrbData4Num3":25,"_OrbData5Num3":10,"_UniqueGrowMaterial1Num3":0,"_UniqueGrowMaterial2Num3":0,"_GrowMaterialNum3":1,"_OrbData1Id4":104001053,"_OrbData2Id4":104001001,"_OrbData3Id4":104002051,"_OrbData4Id4":104002052,"_OrbData5Id4":104003002,"_OrbData1Num4":7,"_OrbData2Num4":3,"_OrbData3Num4":30,"_OrbData4Num4":12,"_OrbData5Num4":1,"_UniqueGrowMaterial1Num4":0,"_UniqueGrowMaterial2Num4":0,"_GrowMaterialNum4":1,"_OrbData1Id5":0,"_OrbData2Id5":0,"_OrbData3Id5":0,"_OrbData4Id5":0,"_OrbData5Id5":0,"_OrbData1Num5":0,"_OrbData2Num5":0,"_OrbData3Num5":0,"_OrbData4Num5":0,"_OrbData5Num5":0,"_UniqueGrowMaterial1Num5":1,"_UniqueGrowMaterial2Num5":0,"_GrowMaterialNum5":1},{"_Id":1050114,"_OrbData1Id1":104001041,"_OrbData2Id1":104001042,"_OrbData3Id1":0,"_OrbData4Id1":0,"_OrbData5Id1":0,"_OrbData1Num1":10,"_OrbData2Num1":1,"_OrbData3Num1":0,"_OrbData4Num1":0,"_OrbData5Num1":0,"_UniqueGrowMaterial1Num1":0,"_UniqueGrowMaterial2Num1":0,"_GrowMaterialNum1":1,"_OrbData1Id2":104001041,"_OrbData2Id2":104001042,"_OrbData3Id2":104001043,"_OrbData4Id2":0,"_OrbData5Id2":0,"_OrbData1Num2":20,"_OrbData2Num2":5,"_OrbData3Num2":1,"_OrbData4Num2":0,"_OrbData5Num2":0,"_UniqueGrowMaterial1Num2":0,"_UniqueGrowMaterial2Num2":0,"_GrowMaterialNum2":1,"_OrbData1Id3":104001042,"_OrbData2Id3":104001043,"_OrbData3Id3":104001001,"_OrbData4Id3":104002041,"_OrbData5Id3":104002042,"_OrbData1Num3":10,"_OrbData2Num3":5,"_OrbData3Num3":1,"_OrbData4Num3":25,"_OrbData5Num3":10,"_UniqueGrowMaterial1Num3":0,"_UniqueGrowMaterial2Num3":0,"_GrowMaterialNum3":1,"_OrbData1Id4":104001043,"_OrbData2Id4":104001001,"_OrbData3Id4":104002041,"_OrbData4Id4":104002042,"_OrbData5Id4":104003002,"_OrbData1Num4":7,"_OrbData2Num4":3,"_OrbData3Num4":30,"_OrbData4Num4":12,"_OrbData5Num4":1,"_UniqueGrowMaterial1Num4":0,"_UniqueGrowMaterial2Num4":0,"_GrowMaterialNum4":1,"_OrbData1Id5":208040011,"_OrbData2Id5":0,"_OrbData3Id5":0,"_OrbData4Id5":0,"_OrbData5Id5":0,"_OrbData1Num5":1,"_OrbData2Num5":0,"_OrbData3Num5":0,"_OrbData4Num5":0,"_OrbData5Num5":0,"_UniqueGrowMaterial1Num5":0,"_UniqueGrowMaterial2Num5":0,"_GrowMaterialNum5":1},{"_Id":1050112,"_OrbData1Id1":104001021,"_OrbData2Id1":104001022,"_OrbData3Id1":0,"_OrbData4Id1":0,"_OrbData5Id1":0,"_OrbData1Num1":10,"_OrbData2Num1":1,"_OrbData3Num1":0,"_OrbData4Num1":0,"_OrbData5Num1":0,"_UniqueGrowMaterial1Num1":0,"_UniqueGrowMaterial2Num1":0,"_GrowMaterialNum1":1,"_OrbData1Id2":104001021,"_OrbData2Id2":104001022,"_OrbData3Id2":104001023,"_OrbData4Id2":0,"_OrbData5Id2":0,"_OrbData1Num2":20,"_OrbData2Num2":5,"_OrbData3Num2":1,"_OrbData4Num2":0,"_OrbData5Num2":0,"_UniqueGrowMaterial1Num2":0,"_UniqueGrowMaterial2Num2":0,"_GrowMaterialNum2":1,"_OrbData1Id3":104001022,"_OrbData2Id3":104001023,"_OrbData3Id3":104001001,"_OrbData4Id3":104002021,"_OrbData5Id3":104002022,"_OrbData1Num3":10,"_OrbData2Num3":5,"_OrbData3Num3":1,"_OrbData4Num3":25,"_OrbData5Num3":10,"_UniqueGrowMaterial1Num3":0,"_UniqueGrowMaterial2Num3":0,"_GrowMaterialNum3":1,"_OrbData1Id4":104001023,"_OrbData2Id4":104001001,"_OrbData3Id4":104002021,"_OrbData4Id4":104002022,"_OrbData5Id4":104003002,"_OrbData1Num4":7,"_OrbData2Num4":3,"_OrbData3Num4":30,"_OrbData4Num4":12,"_OrbData5Num4":1,"_UniqueGrowMaterial1Num4":0,"_UniqueGrowMaterial2Num4":0,"_GrowMaterialNum4":1,"_OrbData1Id5":208020011,"_OrbData2Id5":0,"_OrbData3Id5":0,"_OrbData4Id5":0,"_OrbData5Id5":0,"_OrbData1Num5":1,"_OrbData2Num5":0,"_OrbData3Num5":0,"_OrbData4Num5":0,"_OrbData5Num5":0,"_UniqueGrowMaterial1Num5":0,"_UniqueGrowMaterial2Num5":0,"_GrowMaterialNum5":1},{"_Id":1050113,"_OrbData1Id1":104001031,"_OrbData2Id1":104001032,"_OrbData3Id1":0,"_OrbData4Id1":0,"_OrbData5Id1":0,"_OrbData1Num1":10,"_OrbData2Num1":1,"_OrbData3Num1":0,"_OrbData4Num1":0,"_OrbData5Num1":0,"_UniqueGrowMaterial1Num1":0,"_UniqueGrowMaterial2Num1":0,"_GrowMaterialNum1":1,"_OrbData1Id2":104001031,"_OrbData2Id2":104001032,"_OrbData3Id2":104001033,"_OrbData4Id2":0,"_OrbData5Id2":0,"_OrbData1Num2":20,"_OrbData2Num2":5,"_OrbData3Num2":1,"_OrbData4Num2":0,"_OrbData5Num2":0,"_UniqueGrowMaterial1Num2":0,"_UniqueGrowMaterial2Num2":0,"_GrowMaterialNum2":1,"_OrbData1Id3":104001032,"_OrbData2Id3":104001033,"_OrbData3Id3":104001001,"_OrbData4Id3":104002031,"_OrbData5Id3":104002032,"_OrbData1Num3":10,"_OrbData2Num3":5,"_OrbData3Num3":1,"_OrbData4Num3":25,"_OrbData5Num3":10,"_UniqueGrowMaterial1Num3":0,"_UniqueGrowMaterial2Num3":0,"_GrowMaterialNum3":1,"_OrbData1Id4":104001033,"_OrbData2Id4":104001001,"_OrbData3Id4":104002031,"_OrbData4Id4":104002032,"_OrbData5Id4":104003002,"_OrbData1Num4":7,"_OrbData2Num4":3,"_OrbData3Num4":30,"_OrbData4Num4":12,"_OrbData5Num4":1,"_UniqueGrowMaterial1Num4":0,"_UniqueGrowMaterial2Num4":0,"_GrowMaterialNum4":1,"_OrbData1Id5":208030011,"_OrbData2Id5":0,"_OrbData3Id5":0,"_OrbData4Id5":0,"_OrbData5Id5":0,"_OrbData1Num5":1,"_OrbData2Num5":0,"_OrbData3Num5":0,"_OrbData4Num5":0,"_OrbData5Num5":0,"_UniqueGrowMaterial1Num5":0,"_UniqueGrowMaterial2Num5":0,"_GrowMaterialNum5":1},{"_Id":1040112,"_OrbData1Id1":104001021,"_OrbData2Id1":104001022,"_OrbData3Id1":0,"_OrbData4Id1":0,"_OrbData5Id1":0,"_OrbData1Num1":8,"_OrbData2Num1":1,"_OrbData3Num1":0,"_OrbData4Num1":0,"_OrbData5Num1":0,"_UniqueGrowMaterial1Num1":0,"_UniqueGrowMaterial2Num1":0,"_GrowMaterialNum1":1,"_OrbData1Id2":104001021,"_OrbData2Id2":104001022,"_OrbData3Id2":104001023,"_OrbData4Id2":0,"_OrbData5Id2":0,"_OrbData1Num2":15,"_OrbData2Num2":4,"_OrbData3Num2":1,"_OrbData4Num2":0,"_OrbData5Num2":0,"_UniqueGrowMaterial1Num2":0,"_UniqueGrowMaterial2Num2":0,"_GrowMaterialNum2":1,"_OrbData1Id3":104001022,"_OrbData2Id3":104001023,"_OrbData3Id3":104001001,"_OrbData4Id3":104002021,"_OrbData5Id3":104002022,"_OrbData1Num3":8,"_OrbData2Num3":4,"_OrbData3Num3":1,"_OrbData4Num3":20,"_OrbData5Num3":8,"_UniqueGrowMaterial1Num3":0,"_UniqueGrowMaterial2Num3":0,"_GrowMaterialNum3":1,"_OrbData1Id4":104001023,"_OrbData2Id4":104001001,"_OrbData3Id4":104002021,"_OrbData4Id4":104002022,"_OrbData5Id4":104003001,"_OrbData1Num4":5,"_OrbData2Num4":2,"_OrbData3Num4":25,"_OrbData4Num4":10,"_OrbData5Num4":2,"_UniqueGrowMaterial1Num4":0,"_UniqueGrowMaterial2Num4":0,"_GrowMaterialNum4":1,"_OrbData1Id5":208020021,"_OrbData2Id5":0,"_OrbData3Id5":0,"_OrbData4Id5":0,"_OrbData5Id5":0,"_OrbData1Num5":1,"_OrbData2Num5":0,"_OrbData3Num5":0,"_OrbData4Num5":0,"_OrbData5Num5":0,"_UniqueGrowMaterial1Num5":0,"_UniqueGrowMaterial2Num5":0,"_GrowMaterialNum5":1},{"_Id":1050115,"_OrbData1Id1":104001051,"_OrbData2Id1":104001052,"_OrbData3Id1":0,"_OrbData4Id1":0,"_OrbData5Id1":0,"_OrbData1Num1":10,"_OrbData2Num1":1,"_OrbData3Num1":0,"_OrbData4Num1":0,"_OrbData5Num1":0,"_UniqueGrowMaterial1Num1":0,"_UniqueGrowMaterial2Num1":0,"_GrowMaterialNum1":1,"_OrbData1Id2":104001051,"_OrbData2Id2":104001052,"_OrbData3Id2":104001053,"_OrbData4Id2":0,"_OrbData5Id2":0,"_OrbData1Num2":20,"_OrbData2Num2":5,"_OrbData3Num2":1,"_OrbData4Num2":0,"_OrbData5Num2":0,"_UniqueGrowMaterial1Num2":0,"_UniqueGrowMaterial2Num2":0,"_GrowMaterialNum2":1,"_OrbData1Id3":104001052,"_OrbData2Id3":104001053,"_OrbData3Id3":104001001,"_OrbData4Id3":104002051,"_OrbData5Id3":104002052,"_OrbData1Num3":10,"_OrbData2Num3":5,"_OrbData3Num3":1,"_OrbData4Num3":25,"_OrbData5Num3":10,"_UniqueGrowMaterial1Num3":0,"_UniqueGrowMaterial2Num3":0,"_GrowMaterialNum3":1,"_OrbData1Id4":104001053,"_OrbData2Id4":104001001,"_OrbData3Id4":104002051,"_OrbData4Id4":104002052,"_OrbData5Id4":104003002,"_OrbData1Num4":7,"_OrbData2Num4":3,"_OrbData3Num4":30,"_OrbData4Num4":12,"_OrbData5Num4":1,"_UniqueGrowMaterial1Num4":0,"_UniqueGrowMaterial2Num4":0,"_GrowMaterialNum4":1,"_OrbData1Id5":208050011,"_OrbData2Id5":0,"_OrbData3Id5":0,"_OrbData4Id5":0,"_OrbData5Id5":0,"_OrbData1Num5":1,"_OrbData2Num5":0,"_OrbData3Num5":0,"_OrbData4Num5":0,"_OrbData5Num5":0,"_UniqueGrowMaterial1Num5":0,"_UniqueGrowMaterial2Num5":0,"_GrowMaterialNum5":1},{"_Id":1050111,"_OrbData1Id1":104001011,"_OrbData2Id1":104001012,"_OrbData3Id1":0,"_OrbData4Id1":0,"_OrbData5Id1":0,"_OrbData1Num1":10,"_OrbData2Num1":1,"_OrbData3Num1":0,"_OrbData4Num1":0,"_OrbData5Num1":0,"_UniqueGrowMaterial1Num1":0,"_UniqueGrowMaterial2Num1":0,"_GrowMaterialNum1":1,"_OrbData1Id2":104001011,"_OrbData2Id2":104001012,"_OrbData3Id2":104001013,"_OrbData4Id2":0,"_OrbData5Id2":0,"_OrbData1Num2":20,"_OrbData2Num2":5,"_OrbData3Num2":1,"_OrbData4Num2":0,"_OrbData5Num2":0,"_UniqueGrowMaterial1Num2":0,"_UniqueGrowMaterial2Num2":0,"_GrowMaterialNum2":1,"_OrbData1Id3":104001012,"_OrbData2Id3":104001013,"_OrbData3Id3":104001001,"_OrbData4Id3":104002011,"_OrbData5Id3":104002012,"_OrbData1Num3":10,"_OrbData2Num3":5,"_OrbData3Num3":1,"_OrbData4Num3":25,"_OrbData5Num3":10,"_UniqueGrowMaterial1Num3":0,"_UniqueGrowMaterial2Num3":0,"_GrowMaterialNum3":1,"_OrbData1Id4":104001013,"_OrbData2Id4":104001001,"_OrbData3Id4":104002011,"_OrbData4Id4":104002012,"_OrbData5Id4":104003002,"_OrbData1Num4":7,"_OrbData2Num4":3,"_OrbData3Num4":30,"_OrbData4Num4":12,"_OrbData5Num4":1,"_UniqueGrowMaterial1Num4":0,"_UniqueGrowMaterial2Num4":0,"_GrowMaterialNum4":1,"_OrbData1Id5":208010011,"_OrbData2Id5":0,"_OrbData3Id5":0,"_OrbData4Id5":0,"_OrbData5Id5":0,"_OrbData1Num5":1,"_OrbData2Num5":0,"_OrbData3Num5":0,"_OrbData4Num5":0,"_OrbData5Num5":0,"_UniqueGrowMaterial1Num5":0,"_UniqueGrowMaterial2Num5":0,"_GrowMaterialNum5":1}]