[
    {
        "_Id": 102101,
        "_AddMaxDragonStorage": 0,
        "_EntityType": 18,
        "_EntityId": 0,
        "_EntityQuantity": 2000
    },
    {
        "_Id": 102102,
        "_AddMaxDragonStorage": 0,
        "_EntityType": 17,
        "_EntityId": 10101,
        "_EntityQuantity": 1
    },
    {
        "_Id": 102201,
        "_AddMaxDragonStorage": 5,
        "_EntityType": 0,
        "_EntityId": 0,
        "_EntityQuantity": 0
    },
    {
        "_Id": 102202,
        "_AddMaxDragonStorage": 0,
        "_EntityType": 4,
        "_EntityId": 0,
        "_EntityQuantity": 20000
    },
    {
        "_Id": 102301,
        "_AddMaxDragonStorage": 5,
        "_EntityType": 0,
        "_EntityId": 0,
        "_EntityQuantity": 0
    },
    {
        "_Id": 102302,
        "_AddMaxDragonStorage": 5,
        "_EntityType": 0,
        "_EntityId": 0,
        "_EntityQuantity": 0
    },
    {
        "_Id": 104101,
        "_AddMaxDragonStorage": 0,
        "_EntityType": 8,
        "_EntityId": 101001003,
        "_EntityQuantity": 5
    },
    {
        "_Id": 104102,
        "_AddMaxDragonStorage": 0,
        "_EntityType": 18,
        "_EntityId": 0,
        "_EntityQuantity": 3000
    },
    {
        "_Id": 104201,
        "_AddMaxDragonStorage": 0,
        "_EntityType": 17,
        "_EntityId": 10101,
        "_EntityQuantity": 1
    },
    {
        "_Id": 104202,
        "_AddMaxDragonStorage": 0,
        "_EntityType": 2,
        "_EntityId": 100603,
        "_EntityQuantity": 1
    },
    {
        "_Id": 104301,
        "_AddMaxDragonStorage": 0,
        "_EntityType": 8,
        "_EntityId": 116001001,
        "_EntityQuantity": 10
    },
    {
        "_Id": 104302,
        "_AddMaxDragonStorage": 0,
        "_EntityType": 8,
        "_EntityId": 117001001,
        "_EntityQuantity": 10
    },
    {
        "_Id": 106101,
        "_AddMaxDragonStorage": 5,
        "_EntityType": 0,
        "_EntityId": 0,
        "_EntityQuantity": 0
    },
    {
        "_Id": 106201,
        "_AddMaxDragonStorage": 5,
        "_EntityType": 0,
        "_EntityId": 0,
        "_EntityQuantity": 0
    },
    {
        "_Id": 106301,
        "_AddMaxDragonStorage": 5,
        "_EntityType": 0,
        "_EntityId": 0,
        "_EntityQuantity": 0
    },
    {
        "_Id": 107101,
        "_AddMaxDragonStorage": 0,
        "_EntityType": 4,
        "_EntityId": 0,
        "_EntityQuantity": 100000
    },
    {
        "_Id": 107102,
        "_AddMaxDragonStorage": 5,
        "_EntityType": 0,
        "_EntityId": 0,
        "_EntityQuantity": 0
    },
    {
        "_Id": 107201,
        "_AddMaxDragonStorage": 0,
        "_EntityType": 4,
        "_EntityId": 0,
        "_EntityQuantity": 150000
    },
    {
        "_Id": 107202,
        "_AddMaxDragonStorage": 5,
        "_EntityType": 0,
        "_EntityId": 0,
        "_EntityQuantity": 0
    },
    {
        "_Id": 107301,
        "_AddMaxDragonStorage": 0,
        "_EntityType": 8,
        "_EntityId": 122001001,
        "_EntityQuantity": 10
    },
    {
        "_Id": 107302,
        "_AddMaxDragonStorage": 0,
        "_EntityType": 8,
        "_EntityId": 123001001,
        "_EntityQuantity": 10
    },
    {
        "_Id": 108101,
        "_AddMaxDragonStorage": 5,
        "_EntityType": 0,
        "_EntityId": 0,
        "_EntityQuantity": 0
    },
    {
        "_Id": 108102,
        "_AddMaxDragonStorage": 5,
        "_EntityType": 0,
        "_EntityId": 0,
        "_EntityQuantity": 0
    },
    {
        "_Id": 108201,
        "_AddMaxDragonStorage": 5,
        "_EntityType": 0,
        "_EntityId": 0,
        "_EntityQuantity": 0
    },
    {
        "_Id": 108202,
        "_AddMaxDragonStorage": 5,
        "_EntityType": 0,
        "_EntityId": 0,
        "_EntityQuantity": 0
    },
    {
        "_Id": 108301,
        "_AddMaxDragonStorage": 0,
        "_EntityType": 8,
        "_EntityId": 122001001,
        "_EntityQuantity": 10
    },
    {
        "_Id": 108302,
        "_AddMaxDragonStorage": 0,
        "_EntityType": 8,
        "_EntityId": 123001001,
        "_EntityQuantity": 10
    },
    {
        "_Id": 109101,
        "_AddMaxDragonStorage": 5,
        "_EntityType": 0,
        "_EntityId": 0,
        "_EntityQuantity": 0
    },
    {
        "_Id": 109201,
        "_AddMaxDragonStorage": 5,
        "_EntityType": 0,
        "_EntityId": 0,
        "_EntityQuantity": 0
    },
    {
        "_Id": 109301,
        "_AddMaxDragonStorage": 0,
        "_EntityType": 8,
        "_EntityId": 116001001,
        "_EntityQuantity": 10
    },
    {
        "_Id": 110101,
        "_AddMaxDragonStorage": 0,
        "_EntityType": 8,
        "_EntityId": 116001001,
        "_EntityQuantity": 10
    },
    {
        "_Id": 110201,
        "_AddMaxDragonStorage": 0,
        "_EntityType": 8,
        "_EntityId": 117001001,
        "_EntityQuantity": 10
    },
    {
        "_Id": 110301,
        "_AddMaxDragonStorage": 0,
        "_EntityType": 8,
        "_EntityId": 117001001,
        "_EntityQuantity": 10
    },
    {
        "_Id": 111101,
        "_AddMaxDragonStorage": 0,
        "_EntityType": 8,
        "_EntityId": 122001001,
        "_EntityQuantity": 10
    },
    {
        "_Id": 111201,
        "_AddMaxDragonStorage": 0,
        "_EntityType": 8,
        "_EntityId": 123001001,
        "_EntityQuantity": 10
    },
    {
        "_Id": 111301,
        "_AddMaxDragonStorage": 5,
        "_EntityType": 0,
        "_EntityId": 0,
        "_EntityQuantity": 0
    },
    {
        "_Id": 112101,
        "_AddMaxDragonStorage": 0,
        "_EntityType": 8,
        "_EntityId": 117001001,
        "_EntityQuantity": 10
    },
    {
        "_Id": 112201,
        "_AddMaxDragonStorage": 0,
        "_EntityType": 8,
        "_EntityId": 116001001,
        "_EntityQuantity": 10
    },
    {
        "_Id": 112301,
        "_AddMaxDragonStorage": 0,
        "_EntityType": 8,
        "_EntityId": 122001001,
        "_EntityQuantity": 10
    },
    {
        "_Id": 113101,
        "_AddMaxDragonStorage": 0,
        "_EntityType": 8,
        "_EntityId": 123001001,
        "_EntityQuantity": 10
    },
    {
        "_Id": 113201,
        "_AddMaxDragonStorage": 0,
        "_EntityType": 8,
        "_EntityId": 122001001,
        "_EntityQuantity": 10
    },
    {
        "_Id": 113301,
        "_AddMaxDragonStorage": 0,
        "_EntityType": 8,
        "_EntityId": 123001001,
        "_EntityQuantity": 10
    },
    {
        "_Id": 114101,
        "_AddMaxDragonStorage": 0,
        "_EntityType": 8,
        "_EntityId": 116001001,
        "_EntityQuantity": 10
    },
    {
        "_Id": 114201,
        "_AddMaxDragonStorage": 0,
        "_EntityType": 8,
        "_EntityId": 117001001,
        "_EntityQuantity": 10
    },
    {
        "_Id": 114301,
        "_AddMaxDragonStorage": 0,
        "_EntityType": 8,
        "_EntityId": 116001001,
        "_EntityQuantity": 10
    },
    {
        "_Id": 115101,
        "_AddMaxDragonStorage": 0,
        "_EntityType": 8,
        "_EntityId": 122001001,
        "_EntityQuantity": 10
    },
    {
        "_Id": 115201,
        "_AddMaxDragonStorage": 0,
        "_EntityType": 8,
        "_EntityId": 123001001,
        "_EntityQuantity": 10
    },
    {
        "_Id": 115301,
        "_AddMaxDragonStorage": 0,
        "_EntityType": 8,
        "_EntityId": 117001001,
        "_EntityQuantity": 10
    },
    {
        "_Id": 116101,
        "_AddMaxDragonStorage": 0,
        "_EntityType": 8,
        "_EntityId": 117001001,
        "_EntityQuantity": 10
    },
    {
        "_Id": 116201,
        "_AddMaxDragonStorage": 0,
        "_EntityType": 8,
        "_EntityId": 122001001,
        "_EntityQuantity": 10
    },
    {
        "_Id": 116301,
        "_AddMaxDragonStorage": 0,
        "_EntityType": 8,
        "_EntityId": 123001001,
        "_EntityQuantity": 10
    },
    {
        "_Id": 117101,
        "_AddMaxDragonStorage": 0,
        "_EntityType": 8,
        "_EntityId": 123001001,
        "_EntityQuantity": 10
    },
    {
        "_Id": 117201,
        "_AddMaxDragonStorage": 0,
        "_EntityType": 8,
        "_EntityId": 122001001,
        "_EntityQuantity": 10
    },
    {
        "_Id": 117301,
        "_AddMaxDragonStorage": 0,
        "_EntityType": 8,
        "_EntityId": 116001001,
        "_EntityQuantity": 10
    },
    {
        "_Id": 118101,
        "_AddMaxDragonStorage": 0,
        "_EntityType": 8,
        "_EntityId": 116001001,
        "_EntityQuantity": 10
    },
    {
        "_Id": 118201,
        "_AddMaxDragonStorage": 0,
        "_EntityType": 8,
        "_EntityId": 123001001,
        "_EntityQuantity": 10
    },
    {
        "_Id": 118301,
        "_AddMaxDragonStorage": 0,
        "_EntityType": 8,
        "_EntityId": 117001001,
        "_EntityQuantity": 10
    },
    {
        "_Id": 119101,
        "_AddMaxDragonStorage": 0,
        "_EntityType": 8,
        "_EntityId": 122001001,
        "_EntityQuantity": 10
    },
    {
        "_Id": 119201,
        "_AddMaxDragonStorage": 0,
        "_EntityType": 8,
        "_EntityId": 116001001,
        "_EntityQuantity": 10
    },
    {
        "_Id": 119301,
        "_AddMaxDragonStorage": 0,
        "_EntityType": 8,
        "_EntityId": 123001001,
        "_EntityQuantity": 10
    },
    {
        "_Id": 120101,
        "_AddMaxDragonStorage": 0,
        "_EntityType": 8,
        "_EntityId": 117001001,
        "_EntityQuantity": 10
    },
    {
        "_Id": 120201,
        "_AddMaxDragonStorage": 0,
        "_EntityType": 8,
        "_EntityId": 122001001,
        "_EntityQuantity": 10
    },
    {
        "_Id": 120301,
        "_AddMaxDragonStorage": 0,
        "_EntityType": 8,
        "_EntityId": 116001001,
        "_EntityQuantity": 10
    },
    {
        "_Id": 121101,
        "_AddMaxDragonStorage": 0,
        "_EntityType": 8,
        "_EntityId": 123001001,
        "_EntityQuantity": 10
    },
    {
        "_Id": 121201,
        "_AddMaxDragonStorage": 0,
        "_EntityType": 8,
        "_EntityId": 117001001,
        "_EntityQuantity": 10
    },
    {
        "_Id": 121301,
        "_AddMaxDragonStorage": 0,
        "_EntityType": 8,
        "_EntityId": 122001001,
        "_EntityQuantity": 10
    },
    {
        "_Id": 122101,
        "_AddMaxDragonStorage": 0,
        "_EntityType": 8,
        "_EntityId": 116001001,
        "_EntityQuantity": 10
    },
    {
        "_Id": 122201,
        "_AddMaxDragonStorage": 0,
        "_EntityType": 8,
        "_EntityId": 123001001,
        "_EntityQuantity": 10
    },
    {
        "_Id": 122301,
        "_AddMaxDragonStorage": 0,
        "_EntityType": 8,
        "_EntityId": 117001001,
        "_EntityQuantity": 10
    },
    {
        "_Id": 123101,
        "_AddMaxDragonStorage": 0,
        "_EntityType": 8,
        "_EntityId": 122001001,
        "_EntityQuantity": 10
    },
    {
        "_Id": 123201,
        "_AddMaxDragonStorage": 0,
        "_EntityType": 8,
        "_EntityId": 116001001,
        "_EntityQuantity": 10
    },
    {
        "_Id": 123301,
        "_AddMaxDragonStorage": 0,
        "_EntityType": 8,
        "_EntityId": 123001001,
        "_EntityQuantity": 10
    },
    {
        "_Id": 124101,
        "_AddMaxDragonStorage": 0,
        "_EntityType": 8,
        "_EntityId": 117001001,
        "_EntityQuantity": 10
    },
    {
        "_Id": 124201,
        "_AddMaxDragonStorage": 0,
        "_EntityType": 8,
        "_EntityId": 122001001,
        "_EntityQuantity": 10
    },
    {
        "_Id": 124301,
        "_AddMaxDragonStorage": 0,
        "_EntityType": 8,
        "_EntityId": 116001001,
        "_EntityQuantity": 10
    },
    {
        "_Id": 125101,
        "_AddMaxDragonStorage": 0,
        "_EntityType": 8,
        "_EntityId": 123001001,
        "_EntityQuantity": 10
    },
    {
        "_Id": 125201,
        "_AddMaxDragonStorage": 0,
        "_EntityType": 8,
        "_EntityId": 117001001,
        "_EntityQuantity": 10
    },
    {
        "_Id": 125301,
        "_AddMaxDragonStorage": 0,
        "_EntityType": 8,
        "_EntityId": 122001001,
        "_EntityQuantity": 10
    },
    {
        "_Id": 126101,
        "_AddMaxDragonStorage": 0,
        "_EntityType": 8,
        "_EntityId": 116001001,
        "_EntityQuantity": 10
    },
    {
        "_Id": 126201,
        "_AddMaxDragonStorage": 0,
        "_EntityType": 8,
        "_EntityId": 123001001,
        "_EntityQuantity": 10
    },
    {
        "_Id": 126301,
        "_AddMaxDragonStorage": 0,
        "_EntityType": 8,
        "_EntityId": 117001001,
        "_EntityQuantity": 10
    }
]